<annotation>
	<folder>revamped_data</folder>
	<filename>IMG_20200609_140004.jpg</filename>
	<path>C:\tensorflow1\models\research\object_detection\images\train\IMG_20200609_140004.jpg</path>
	<source>
		<database>Unknown</database>
	</source>
	<size>
		<width>1024</width>
		<height>768</height>
		<depth>3</depth>
	</size>
	<segmented>0</segmented>
	<object>
		<name>5D</name>
		<pose>Unspecified</pose>
		<truncated>0</truncated>
		<difficult>0</difficult>
		<bndbox>
			<xmin>134</xmin>
			<ymin>69</ymin>
			<xmax>184</xmax>
			<ymax>186</ymax>
		</bndbox>
	</object>
	<object>
		<name>3D</name>
		<pose>Unspecified</pose>
		<truncated>0</truncated>
		<difficult>0</difficult>
		<bndbox>
			<xmin>113</xmin>
			<ymin>205</ymin>
			<xmax>166</xmax>
			<ymax>324</ymax>
		</bndbox>
	</object>
	<object>
		<name>QS</name>
		<pose>Unspecified</pose>
		<truncated>0</truncated>
		<difficult>0</difficult>
		<bndbox>
			<xmin>573</xmin>
			<ymin>78</ymin>
			<xmax>610</xmax>
			<ymax>176</ymax>
		</bndbox>
	</object>
	<object>
		<name>2H</name>
		<pose>Unspecified</pose>
		<truncated>0</truncated>
		<difficult>0</difficult>
		<bndbox>
			<xmin>551</xmin>
			<ymin>202</ymin>
			<xmax>599</xmax>
			<ymax>308</ymax>
		</bndbox>
	</object>
	<object>
		<name>5D</name>
		<pose>Unspecified</pose>
		<truncated>0</truncated>
		<difficult>0</difficult>
		<bndbox>
			<xmin>401</xmin>
			<ymin>69</ymin>
			<xmax>451</xmax>
			<ymax>186</ymax>
		</bndbox>
	</object>
	<object>
		<name>3D</name>
		<pose>Unspecified</pose>
		<truncated>0</truncated>
		<difficult>0</difficult>
		<bndbox>
			<xmin>391</xmin>
			<ymin>196</ymin>
			<xmax>444</xmax>
			<ymax>315</ymax>
		</bndbox>
	</object>
	<object>
		<name>QS</name>
		<pose>Unspecified</pose>
		<truncated>0</truncated>
		<difficult>0</difficult>
		<bndbox>
			<xmin>822</xmin>
			<ymin>115</ymin>
			<xmax>859</xmax>
			<ymax>213</ymax>
		</bndbox>
	</object>
	<object>
		<name>2H</name>
		<pose>Unspecified</pose>
		<truncated>0</truncated>
		<difficult>0</difficult>
		<bndbox>
			<xmin>818</xmin>
			<ymin>239</ymin>
			<xmax>866</xmax>
			<ymax>345</ymax>
		</bndbox>
	</object>
</annotation>
